CHANGELOG.txt
LICENSE.txt
MANIFEST.in
Module Contents.txt
README.txt
setup.py
Ekidna/__init__.py
Ekidna.egg-info/PKG-INFO
Ekidna.egg-info/SOURCES.txt
Ekidna.egg-info/dependency_links.txt
Ekidna.egg-info/top_level.txt