Metadata-Version: 2.1
Name: Ekidna
Version: 0.0.8
Summary: Electrochemistry data analysis tools
Home-page: 
Author: OzymandiasTheDead
Author-email: jacob@ekidnasensing.com
License: MIT
Keywords: Ekidna
Classifier: Development Status :: 2 - Pre-Alpha
Classifier: Intended Audience :: Science/Research
Classifier: Operating System :: Microsoft :: Windows :: Windows 10
Classifier: License :: OSI Approved :: MIT License
Classifier: Programming Language :: Python :: 3
License-File: LICENSE.txt
